<annotation>
	<folder>original</folder>
	<filename>00000090.png</filename>
	<path>C:\Users\SAGAR DEEP\Desktop\Images_png\original\00000090.png</path>
	<source>
		<database>Unknown</database>
	</source>
	<size>
		<width>2396</width>
		<height>3152</height>
		<depth>3</depth>
	</size>
	<segmented>0</segmented>
	<object>
		<name>Title</name>
		<pose>Unspecified</pose>
		<truncated>0</truncated>
		<difficult>0</difficult>
		<bndbox>
			<xmin>9</xmin>
			<ymin>50</ymin>
			<xmax>2241</xmax>
			<ymax>176</ymax>
		</bndbox>
	</object>
	<object>
		<name>Figure</name>
		<pose>Unspecified</pose>
		<truncated>0</truncated>
		<difficult>0</difficult>
		<bndbox>
			<xmin>77</xmin>
			<ymin>231</ymin>
			<xmax>1574</xmax>
			<ymax>1460</ymax>
		</bndbox>
	</object>
	<object>
		<name>Figure</name>
		<pose>Unspecified</pose>
		<truncated>1</truncated>
		<difficult>0</difficult>
		<bndbox>
			<xmin>1600</xmin>
			<ymin>192</ymin>
			<xmax>2396</xmax>
			<ymax>1324</ymax>
		</bndbox>
	</object>
	<object>
		<name>Caption</name>
		<pose>Unspecified</pose>
		<truncated>0</truncated>
		<difficult>0</difficult>
		<bndbox>
			<xmin>1593</xmin>
			<ymin>1331</ymin>
			<xmax>2322</xmax>
			<ymax>1511</ymax>
		</bndbox>
	</object>
	<object>
		<name>Subtitle</name>
		<pose>Unspecified</pose>
		<truncated>0</truncated>
		<difficult>0</difficult>
		<bndbox>
			<xmin>93</xmin>
			<ymin>1534</ymin>
			<xmax>764</xmax>
			<ymax>1837</ymax>
		</bndbox>
	</object>
	<object>
		<name>Subtitle</name>
		<pose>Unspecified</pose>
		<truncated>0</truncated>
		<difficult>0</difficult>
		<bndbox>
			<xmin>854</xmin>
			<ymin>1543</ymin>
			<xmax>1490</xmax>
			<ymax>1853</ymax>
		</bndbox>
	</object>
	<object>
		<name>Subtitle</name>
		<pose>Unspecified</pose>
		<truncated>0</truncated>
		<difficult>0</difficult>
		<bndbox>
			<xmin>1619</xmin>
			<ymin>1534</ymin>
			<xmax>2225</xmax>
			<ymax>1853</ymax>
		</bndbox>
	</object>
	<object>
		<name>Text</name>
		<pose>Unspecified</pose>
		<truncated>0</truncated>
		<difficult>0</difficult>
		<bndbox>
			<xmin>83</xmin>
			<ymin>1866</ymin>
			<xmax>790</xmax>
			<ymax>2179</ymax>
		</bndbox>
	</object>
	<object>
		<name>Text</name>
		<pose>Unspecified</pose>
		<truncated>0</truncated>
		<difficult>0</difficult>
		<bndbox>
			<xmin>396</xmin>
			<ymin>2179</ymin>
			<xmax>735</xmax>
			<ymax>2637</ymax>
		</bndbox>
	</object>
	<object>
		<name>Text</name>
		<pose>Unspecified</pose>
		<truncated>0</truncated>
		<difficult>0</difficult>
		<bndbox>
			<xmin>845</xmin>
			<ymin>2153</ymin>
			<xmax>1516</xmax>
			<ymax>2718</ymax>
		</bndbox>
	</object>
	<object>
		<name>Text</name>
		<pose>Unspecified</pose>
		<truncated>0</truncated>
		<difficult>0</difficult>
		<bndbox>
			<xmin>1577</xmin>
			<ymin>1885</ymin>
			<xmax>2003</xmax>
			<ymax>2424</ymax>
		</bndbox>
	</object>
	<object>
		<name>Text</name>
		<pose>Unspecified</pose>
		<truncated>0</truncated>
		<difficult>0</difficult>
		<bndbox>
			<xmin>1570</xmin>
			<ymin>2431</ymin>
			<xmax>2132</xmax>
			<ymax>2601</ymax>
		</bndbox>
	</object>
	<object>
		<name>Figure</name>
		<pose>Unspecified</pose>
		<truncated>0</truncated>
		<difficult>0</difficult>
		<bndbox>
			<xmin>74</xmin>
			<ymin>2205</ymin>
			<xmax>387</xmax>
			<ymax>2634</ymax>
		</bndbox>
	</object>
	<object>
		<name>Figure</name>
		<pose>Unspecified</pose>
		<truncated>1</truncated>
		<difficult>0</difficult>
		<bndbox>
			<xmin>25</xmin>
			<ymin>2666</ymin>
			<xmax>2396</xmax>
			<ymax>2924</ymax>
		</bndbox>
	</object>
	<object>
		<name>Figure</name>
		<pose>Unspecified</pose>
		<truncated>0</truncated>
		<difficult>0</difficult>
		<bndbox>
			<xmin>2038</xmin>
			<ymin>1895</ymin>
			<xmax>2293</xmax>
			<ymax>2366</ymax>
		</bndbox>
	</object>
	<object>
		<name>Caption</name>
		<pose>Unspecified</pose>
		<truncated>0</truncated>
		<difficult>0</difficult>
		<bndbox>
			<xmin>616</xmin>
			<ymin>2911</ymin>
			<xmax>980</xmax>
			<ymax>3027</ymax>
		</bndbox>
	</object>
</annotation>
